kw618/__init__.py
kw618/_api.py
kw618/_file_path.py
kw618/_general_utils.py
kw618/_version.py
kw618/settings.py
kw618/k_finance/__init__.py
kw618/k_finance/const.py
kw618/k_finance/const_backup.py
kw618/k_finance/k_vnpy.py
kw618/k_finance/k_vnpy0.py
kw618/k_finance/k_vnpy_backup.py
kw618/k_finance/k_vnpy_backup2.py
kw618/k_finance/k_vnpy_backup3.py
kw618/k_finance/note_quant.py
kw618/k_finance/quant_hc.py
kw618/k_finance/quant_strategy.py
kw618/k_finance/utils_quant.py
kw618/k_finance/utils_quant_backup.py
kw618/k_finance/utils_quant_backup2.py
kw618/k_finance/utils_quant_backup3.py
kw618/k_finance/Arbitrage/__init__.py
kw618/k_finance/Arbitrage/binance_gateway.py
kw618/k_finance/Arbitrage/calData.py
kw618/k_finance/Arbitrage/getData.py
kw618/k_finance/Arbitrage/note.py
kw618/k_finance/Arbitrage/sendOrder.py
kw618/k_finance/Arbitrage/sendOrder_simply.py
kw618/k_finance/Arbitrage/t1.py
kw618/k_finance/Arbitrage/脚本01_查看最优借币.py
kw618/k_finance/Arbitrage/脚本02_转账借币.py
kw618/k_finance/Arbitrage/脚本03_检查实际价差率.py
kw618/k_libs/__init__.py
kw618/k_pandas/__init__.py
kw618/k_pandas/utils_finance.py
kw618/k_pandas/utils_pandas.py
kw618/k_pymongo/__init__.py
kw618/k_pymongo/utils_pymongo.py
kw618/k_pymongo/utils_redis.py
kw618/k_pymysql/__init__.py
kw618/k_pymysql/utils_pymysql.py
kw618/k_python/__init__.py
kw618/k_python/utils_img.py
kw618/k_python/utils_python.py
kw618/k_requests/__init__.py
kw618/k_requests/abuyun_proxies.py
kw618/k_requests/my_cookies.py
kw618/k_requests/ocr.py
kw618/k_requests/robust.py
kw618/k_requests/selenium_login.py
kw618/k_requests/utils_qrcode.py
kw618/k_requests/utils_requests.py
kw618/k_requests/wyy.py
kw618/k_requests/js/__init__.py
kw618/ttt/__init__.py
kw618/ttt/t1.py
kw618-0.3.1.dist-info/METADATA
kw618-0.3.1.dist-info/WHEEL
kw618-0.3.1.dist-info/top_level.txt
kw618-0.3.1.dist-info/RECORD
